foxglove_websocket/__init__.py
foxglove_websocket/types.py
foxglove_websocket/examples/__init__.py
foxglove_websocket/examples/json_server.py
foxglove_websocket/examples/param_server.py
foxglove_websocket/examples/protobuf_server.py
foxglove_websocket/server/__init__.py
foxglove_websocket/server/client_state.py
foxglove_websocket-0.1.2.dist-info/METADATA
foxglove_websocket-0.1.2.dist-info/WHEEL
foxglove_websocket-0.1.2.dist-info/top_level.txt
foxglove_websocket-0.1.2.dist-info/RECORD
