Metadata-Version: 2.1
Name: foxglove-websocket
Version: 0.1.2
Summary: Foxglove WebSocket server
Home-page: https://github.com/foxglove/ws-protocol
License: MIT
Project-URL: GitHub Issues, https://github.com/foxglove/ws-protocol/issues
Project-URL: Foxglove Studio Documentation, https://foxglove.dev/docs
Keywords: foxglove,websocket,robotics,ros,ros2
Classifier: Programming Language :: Python :: 3
Classifier: License :: OSI Approved :: MIT License
Classifier: Operating System :: OS Independent
Requires-Python: >=3.8
Requires-Dist: websockets
Provides-Extra: examples
Requires-Dist: protobuf (>=4) ; extra == 'examples'
Requires-Dist: pyquaternion ; extra == 'examples'
Requires-Dist: foxglove-schemas-protobuf ; extra == 'examples'
